{"v":"5.12.2","fr":60,"ip":400,"op":432,"w":370,"h":433,"nm":"RocketFPS","ddd":0,"assets":[{"id":"comp_0","nm":"stars","fr":59.9400024414063,"layers":[{"ddd":0,"ind":1,"ty":4,"nm":"Shape Layer 15","sr":1,"ks":{"o":{"a":0,"k":100,"ix":11},"r":{"a":0,"k":0,"ix":10},"p":{"a":0,"k":[46.5,326,0],"ix":2,"l":2},"a":{"a":0,"k":[-91,-238,0],"ix":1,"l":2},"s":{"a":0,"k":[100,100,100],"ix":6,"l":2}},"ao":0,"shapes":[{"ty":"gr","it":[{"ty":"rc","d":1,"s":{"a":0,"k":[5,17],"ix":2},"p":{"a":0,"k":[0,0],"ix":3},"r":{"a":0,"k":20,"ix":4},"nm":"Rectangle Path 1","mn":"ADBE Vector Shape - Rect","hd":false},{"ty":"fl","c":{"a":0,"k":[1,1,1,1],"ix":4},"o":{"a":0,"k":100,"ix":5},"r":1,"bm":0,"nm":"Fill 1","mn":"ADBE Vector Graphic - Fill","hd":false},{"ty":"tr","p":{"a":0,"k":[-91,-238],"ix":2},"a":{"a":0,"k":[0,0],"ix":1},"s":{"a":0,"k":[100,100],"ix":3},"r":{"a":0,"k":0,"ix":6},"o":{"a":0,"k":100,"ix":7},"sk":{"a":0,"k":0,"ix":4},"sa":{"a":0,"k":0,"ix":5},"nm":"Transformer "}],"nm":"Rectangle 1","np":2,"cix":2,"bm":0,"ix":1,"mn":"ADBE Vector Group","hd":false}],"ip":0,"op":720.720720720721,"st":0,"ct":1,"bm":0},{"ddd":0,"ind":2,"ty":4,"nm":"Shape Layer 14","sr":1,"ks":{"o":{"a":0,"k":100,"ix":11},"r":{"a":0,"k":0,"ix":10},"p":{"a":0,"k":[319.5,352,0],"ix":2,"l":2},"a":{"a":0,"k":[-91,-238,0],"ix":1,"l":2},"s":{"a":0,"k":[100,100,100],"ix":6,"l":2}},"ao":0,"shapes":[{"ty":"gr","it":[{"ty":"rc","d":1,"s":{"a":0,"k":[5,35],"ix":2},"p":{"a":0,"k":[0,0],"ix":3},"r":{"a":0,"k":20,"ix":4},"nm":"Rectangle Path 1","mn":"ADBE Vector Shape - Rect","hd":false},{"ty":"fl","c":{"a":0,"k":[1,1,1,1],"ix":4},"o":{"a":0,"k":100,"ix":5},"r":1,"bm":0,"nm":"Fill 1","mn":"ADBE Vector Graphic - Fill","hd":false},{"ty":"tr","p":{"a":0,"k":[-91,-238],"ix":2},"a":{"a":0,"k":[0,0],"ix":1},"s":{"a":0,"k":[100,100],"ix":3},"r":{"a":0,"k":0,"ix":6},"o":{"a":0,"k":100,"ix":7},"sk":{"a":0,"k":0,"ix":4},"sa":{"a":0,"k":0,"ix":5},"nm":"Transformer "}],"nm":"Rectangle 1","np":2,"cix":2,"bm":0,"ix":1,"mn":"ADBE Vector Group","hd":false}],"ip":0,"op":720.720720720721,"st":0,"ct":1,"bm":0},{"ddd":0,"ind":3,"ty":4,"nm":"Shape Layer 13","sr":1,"ks":{"o":{"a":0,"k":100,"ix":11},"r":{"a":0,"k":0,"ix":10},"p":{"a":0,"k":[244.5,152,0],"ix":2,"l":2},"a":{"a":0,"k":[-91,-238,0],"ix":1,"l":2},"s":{"a":0,"k":[100,100,100],"ix":6,"l":2}},"ao":0,"shapes":[{"ty":"gr","it":[{"ty":"rc","d":1,"s":{"a":0,"k":[5,37],"ix":2},"p":{"a":0,"k":[0,0],"ix":3},"r":{"a":0,"k":20,"ix":4},"nm":"Rectangle Path 1","mn":"ADBE Vector Shape - Rect","hd":false},{"ty":"fl","c":{"a":0,"k":[1,1,1,1],"ix":4},"o":{"a":0,"k":100,"ix":5},"r":1,"bm":0,"nm":"Fill 1","mn":"ADBE Vector Graphic - Fill","hd":false},{"ty":"tr","p":{"a":0,"k":[-91,-238],"ix":2},"a":{"a":0,"k":[0,0],"ix":1},"s":{"a":0,"k":[100,100],"ix":3},"r":{"a":0,"k":0,"ix":6},"o":{"a":0,"k":100,"ix":7},"sk":{"a":0,"k":0,"ix":4},"sa":{"a":0,"k":0,"ix":5},"nm":"Transformer "}],"nm":"Rectangle 1","np":2,"cix":2,"bm":0,"ix":1,"mn":"ADBE Vector Group","hd":false}],"ip":0,"op":720.720720720721,"st":0,"ct":1,"bm":0},{"ddd":0,"ind":4,"ty":4,"nm":"Shape Layer 12","sr":1,"ks":{"o":{"a":0,"k":100,"ix":11},"r":{"a":0,"k":0,"ix":10},"p":{"a":0,"k":[151.5,109,0],"ix":2,"l":2},"a":{"a":0,"k":[-91,-238,0],"ix":1,"l":2},"s":{"a":0,"k":[100,100,100],"ix":6,"l":2}},"ao":0,"shapes":[{"ty":"gr","it":[{"ty":"rc","d":1,"s":{"a":0,"k":[5,22],"ix":2},"p":{"a":0,"k":[0,0],"ix":3},"r":{"a":0,"k":20,"ix":4},"nm":"Rectangle Path 1","mn":"ADBE Vector Shape - Rect","hd":false},{"ty":"fl","c":{"a":0,"k":[1,1,1,1],"ix":4},"o":{"a":0,"k":100,"ix":5},"r":1,"bm":0,"nm":"Fill 1","mn":"ADBE Vector Graphic - Fill","hd":false},{"ty":"tr","p":{"a":0,"k":[-91,-238],"ix":2},"a":{"a":0,"k":[0,0],"ix":1},"s":{"a":0,"k":[100,100],"ix":3},"r":{"a":0,"k":0,"ix":6},"o":{"a":0,"k":100,"ix":7},"sk":{"a":0,"k":0,"ix":4},"sa":{"a":0,"k":0,"ix":5},"nm":"Transformer "}],"nm":"Rectangle 1","np":2,"cix":2,"bm":0,"ix":1,"mn":"ADBE Vector Group","hd":false}],"ip":0,"op":720.720720720721,"st":0,"ct":1,"bm":0},{"ddd":0,"ind":5,"ty":4,"nm":"Shape Layer 11","sr":1,"ks":{"o":{"a":0,"k":100,"ix":11},"r":{"a":0,"k":0,"ix":10},"p":{"a":0,"k":[291.5,200,0],"ix":2,"l":2},"a":{"a":0,"k":[-91,-238,0],"ix":1,"l":2},"s":{"a":0,"k":[100,100,100],"ix":6,"l":2}},"ao":0,"shapes":[{"ty":"gr","it":[{"ty":"rc","d":1,"s":{"a":0,"k":[5,22],"ix":2},"p":{"a":0,"k":[0,0],"ix":3},"r":{"a":0,"k":20,"ix":4},"nm":"Rectangle Path 1","mn":"ADBE Vector Shape - Rect","hd":false},{"ty":"fl","c":{"a":0,"k":[1,1,1,1],"ix":4},"o":{"a":0,"k":100,"ix":5},"r":1,"bm":0,"nm":"Fill 1","mn":"ADBE Vector Graphic - Fill","hd":false},{"ty":"tr","p":{"a":0,"k":[-91,-238],"ix":2},"a":{"a":0,"k":[0,0],"ix":1},"s":{"a":0,"k":[100,100],"ix":3},"r":{"a":0,"k":0,"ix":6},"o":{"a":0,"k":100,"ix":7},"sk":{"a":0,"k":0,"ix":4},"sa":{"a":0,"k":0,"ix":5},"nm":"Transformer "}],"nm":"Rectangle 1","np":2,"cix":2,"bm":0,"ix":1,"mn":"ADBE Vector Group","hd":false}],"ip":0,"op":720.720720720721,"st":0,"ct":1,"bm":0},{"ddd":0,"ind":6,"ty":4,"nm":"Shape Layer 10","sr":1,"ks":{"o":{"a":0,"k":100,"ix":11},"r":{"a":0,"k":0,"ix":10},"p":{"a":0,"k":[326.5,70,0],"ix":2,"l":2},"a":{"a":0,"k":[-91,-238,0],"ix":1,"l":2},"s":{"a":0,"k":[100,100,100],"ix":6,"l":2}},"ao":0,"shapes":[{"ty":"gr","it":[{"ty":"rc","d":1,"s":{"a":0,"k":[5,22],"ix":2},"p":{"a":0,"k":[0,0],"ix":3},"r":{"a":0,"k":20,"ix":4},"nm":"Rectangle Path 1","mn":"ADBE Vector Shape - Rect","hd":false},{"ty":"fl","c":{"a":0,"k":[1,1,1,1],"ix":4},"o":{"a":0,"k":100,"ix":5},"r":1,"bm":0,"nm":"Fill 1","mn":"ADBE Vector Graphic - Fill","hd":false},{"ty":"tr","p":{"a":0,"k":[-91,-238],"ix":2},"a":{"a":0,"k":[0,0],"ix":1},"s":{"a":0,"k":[100,100],"ix":3},"r":{"a":0,"k":0,"ix":6},"o":{"a":0,"k":100,"ix":7},"sk":{"a":0,"k":0,"ix":4},"sa":{"a":0,"k":0,"ix":5},"nm":"Transformer "}],"nm":"Rectangle 1","np":2,"cix":2,"bm":0,"ix":1,"mn":"ADBE Vector Group","hd":false}],"ip":0,"op":720.720720720721,"st":0,"ct":1,"bm":0},{"ddd":0,"ind":7,"ty":4,"nm":"Shape Layer 9","sr":1,"ks":{"o":{"a":0,"k":100,"ix":11},"r":{"a":0,"k":0,"ix":10},"p":{"a":0,"k":[87.5,227,0],"ix":2,"l":2},"a":{"a":0,"k":[-91,-238,0],"ix":1,"l":2},"s":{"a":0,"k":[100,100,100],"ix":6,"l":2}},"ao":0,"shapes":[{"ty":"gr","it":[{"ty":"rc","d":1,"s":{"a":0,"k":[5,39],"ix":2},"p":{"a":0,"k":[0,0],"ix":3},"r":{"a":0,"k":20,"ix":4},"nm":"Rectangle Path 1","mn":"ADBE Vector Shape - Rect","hd":false},{"ty":"fl","c":{"a":0,"k":[1,1,1,1],"ix":4},"o":{"a":0,"k":100,"ix":5},"r":1,"bm":0,"nm":"Fill 1","mn":"ADBE Vector Graphic - Fill","hd":false},{"ty":"tr","p":{"a":0,"k":[-91,-238],"ix":2},"a":{"a":0,"k":[0,0],"ix":1},"s":{"a":0,"k":[100,100],"ix":3},"r":{"a":0,"k":0,"ix":6},"o":{"a":0,"k":100,"ix":7},"sk":{"a":0,"k":0,"ix":4},"sa":{"a":0,"k":0,"ix":5},"nm":"Transformer "}],"nm":"Rectangle 1","np":2,"cix":2,"bm":0,"ix":1,"mn":"ADBE Vector Group","hd":false}],"ip":0,"op":720.720720720721,"st":0,"ct":1,"bm":0},{"ddd":0,"ind":8,"ty":4,"nm":"Shape Layer 8","sr":1,"ks":{"o":{"a":0,"k":100,"ix":11},"r":{"a":0,"k":0,"ix":10},"p":{"a":0,"k":[36.5,172,0],"ix":2,"l":2},"a":{"a":0,"k":[-91,-238,0],"ix":1,"l":2},"s":{"a":0,"k":[100,100,100],"ix":6,"l":2}},"ao":0,"shapes":[{"ty":"gr","it":[{"ty":"rc","d":1,"s":{"a":0,"k":[5,22],"ix":2},"p":{"a":0,"k":[0,0],"ix":3},"r":{"a":0,"k":20,"ix":4},"nm":"Rectangle Path 1","mn":"ADBE Vector Shape - Rect","hd":false},{"ty":"fl","c":{"a":0,"k":[1,1,1,1],"ix":4},"o":{"a":0,"k":100,"ix":5},"r":1,"bm":0,"nm":"Fill 1","mn":"ADBE Vector Graphic - Fill","hd":false},{"ty":"tr","p":{"a":0,"k":[-91,-238],"ix":2},"a":{"a":0,"k":[0,0],"ix":1},"s":{"a":0,"k":[100,100],"ix":3},"r":{"a":0,"k":0,"ix":6},"o":{"a":0,"k":100,"ix":7},"sk":{"a":0,"k":0,"ix":4},"sa":{"a":0,"k":0,"ix":5},"nm":"Transformer "}],"nm":"Rectangle 1","np":2,"cix":2,"bm":0,"ix":1,"mn":"ADBE Vector Group","hd":false}],"ip":0,"op":720.720720720721,"st":0,"ct":1,"bm":0},{"ddd":0,"ind":9,"ty":4,"nm":"Shape Layer 7","sr":1,"ks":{"o":{"a":0,"k":100,"ix":11},"r":{"a":0,"k":0,"ix":10},"p":{"a":0,"k":[57.5,109,0],"ix":2,"l":2},"a":{"a":0,"k":[-91,-238,0],"ix":1,"l":2},"s":{"a":0,"k":[100,100,100],"ix":6,"l":2}},"ao":0,"shapes":[{"ty":"gr","it":[{"ty":"rc","d":1,"s":{"a":0,"k":[5,22],"ix":2},"p":{"a":0,"k":[0,0],"ix":3},"r":{"a":0,"k":20,"ix":4},"nm":"Rectangle Path 1","mn":"ADBE Vector Shape - Rect","hd":false},{"ty":"fl","c":{"a":0,"k":[1,1,1,1],"ix":4},"o":{"a":0,"k":100,"ix":5},"r":1,"bm":0,"nm":"Fill 1","mn":"ADBE Vector Graphic - Fill","hd":false},{"ty":"tr","p":{"a":0,"k":[-91,-238],"ix":2},"a":{"a":0,"k":[0,0],"ix":1},"s":{"a":0,"k":[100,100],"ix":3},"r":{"a":0,"k":0,"ix":6},"o":{"a":0,"k":100,"ix":7},"sk":{"a":0,"k":0,"ix":4},"sa":{"a":0,"k":0,"ix":5},"nm":"Transformer "}],"nm":"Rectangle 1","np":2,"cix":2,"bm":0,"ix":1,"mn":"ADBE Vector Group","hd":false}],"ip":0,"op":720.720720720721,"st":0,"ct":1,"bm":0}]},{"id":"comp_1","nm":"ion-ios-rocket","fr":59.9400024414063,"layers":[{"ddd":0,"ind":1,"ty":4,"nm":"Ã\u0090Â¡Ã\u0090Â»Ã\u0090Â¾Ã\u0090Â¹ 1 Outlines","sr":1,"ks":{"o":{"a":0,"k":100,"ix":11},"r":{"a":0,"k":0,"ix":10},"p":{"a":0,"k":[52.991,46.009,0],"ix":2,"l":2},"a":{"a":0,"k":[23.351,34.989,0],"ix":1,"l":2},"s":{"a":0,"k":[100,100,100],"ix":6,"l":2}},"ao":0,"shapes":[{"ty":"gr","it":[{"ind":0,"ty":"sh","ix":1,"ks":{"a":0,"k":{"i":[[3.449,0],[0,3.449],[-3.449,0],[0,-3.449]],"o":[[-3.449,0],[0,-3.449],[3.449,0],[0,3.449]],"v":[[0.042,-1.229],[-6.196,-7.466],[0.042,-13.704],[6.279,-7.466]],"c":true},"ix":2},"nm":"Tracé 1","mn":"ADBE Vector Shape - Group","hd":false},{"ind":1,"ty":"sh","ix":2,"ks":{"a":0,"k":{"i":[[7.249,4.544],[0.217,-0.135],[0,-14.065],[-0.393,-2.231],[1.043,-2.654],[-2.148,-2.995],[-0.547,0.672],[0,0],[-0.495,-0.393],[-0.619,0],[0,0],[-0.476,0.392],[-0.805,0.784],[0,0],[-0.505,0.712],[2.933,7.498],[2.343,1.972],[0,2.747]],"o":[[-0.217,-0.135],[-6.991,4.244],[0,2.747],[-2.365,1.973],[-2.923,7.508],[0.505,0.712],[0,0],[0.816,0.795],[0.476,0.392],[0,0],[0.619,0],[0.495,-0.393],[0,0],[0.547,0.672],[2.159,-2.985],[-1.043,-2.653],[0.392,-2.231],[0.041,-14.085]],"v":[[0.383,-34.594],[-0.31,-34.604],[-15.387,1.58],[-14.767,9.036],[-20.178,15.996],[-16.48,34.006],[-14.396,34.067],[-6.939,24.773],[-4.937,26.55],[-3.243,27.148],[3.243,27.148],[4.936,26.55],[6.93,24.784],[14.374,34.067],[16.46,34.006],[20.167,16.006],[14.788,9.057],[15.417,1.59]],"c":true},"ix":2},"nm":"Tracé 2","mn":"ADBE Vector Shape - Group","hd":false},{"ty":"fl","c":{"a":0,"k":[1,1,1,1],"ix":4},"o":{"a":0,"k":100,"ix":5},"r":1,"bm":0,"nm":"Fill 1","mn":"ADBE Vector Graphic - Fill","hd":false},{"ty":"tr","p":{"a":0,"k":[23.35,34.989],"ix":2},"a":{"a":0,"k":[0,0],"ix":1},"s":{"a":0,"k":[100,100],"ix":3},"r":{"a":0,"k":0,"ix":6},"o":{"a":0,"k":100,"ix":7},"sk":{"a":0,"k":0,"ix":4},"sa":{"a":0,"k":0,"ix":5},"nm":"Transformer "}],"nm":"Group 1","np":3,"cix":2,"bm":0,"ix":1,"mn":"ADBE Vector Group","hd":false}],"ip":0,"op":720.720720720721,"st":0,"ct":1,"bm":0},{"ddd":0,"ind":2,"ty":4,"nm":"Ã\u0090Â¡Ã\u0090Â»Ã\u0090Â¾Ã\u0090Â¹ 2 Outlines","sr":1,"ks":{"o":{"a":0,"k":100,"ix":11},"r":{"a":0,"k":0,"ix":10},"p":{"a":0,"k":[53.048,74.347,0],"ix":2,"l":2},"a":{"a":0,"k":[6.978,0.427,0],"ix":1,"l":2},"s":{"a":1,"k":[{"i":{"x":[0.833,0.833,0.833],"y":[0.833,0.833,1]},"o":{"x":[0.167,0.167,0.167],"y":[0.167,0.167,0]},"t":159.159,"s":[100,100,100]},{"i":{"x":[0.833,0.833,0.833],"y":[0.833,0.833,1]},"o":{"x":[0.167,0.167,0.167],"y":[0.167,0.167,0]},"t":164.665,"s":[70,70,100]},{"i":{"x":[0.833,0.833,0.833],"y":[0.833,0.833,1]},"o":{"x":[0.167,0.167,0.167],"y":[0.167,0.167,0]},"t":170.17,"s":[100,100,100]},{"i":{"x":[0.833,0.833,0.833],"y":[0.833,0.833,1]},"o":{"x":[0.167,0.167,0.167],"y":[0.167,0.167,0]},"t":174.675,"s":[70,70,100]},{"i":{"x":[0.833,0.833,0.833],"y":[0.833,0.833,1]},"o":{"x":[0.167,0.167,0.167],"y":[0.167,0.167,0]},"t":180.18,"s":[100,100,100]},{"i":{"x":[0.833,0.833,0.833],"y":[0.833,0.833,1]},"o":{"x":[0.167,0.167,0.167],"y":[0.167,0.167,0]},"t":185.185,"s":[70,70,100]},{"i":{"x":[0.833,0.833,0.833],"y":[0.833,0.833,1]},"o":{"x":[0.167,0.167,0.167],"y":[0.167,0.167,0]},"t":190.691,"s":[100,100,100]},{"i":{"x":[0.833,0.833,0.833],"y":[0.833,0.833,1]},"o":{"x":[0.167,0.167,0.167],"y":[0.167,0.167,0]},"t":195.195,"s":[70,70,100]},{"i":{"x":[0.833,0.833,0.833],"y":[0.833,0.833,1]},"o":{"x":[0.167,0.167,0.167],"y":[0.167,0.167,0]},"t":200.701,"s":[100,100,100]},{"i":{"x":[0.833,0.833,0.833],"y":[0.833,0.833,1]},"o":{"x":[0.167,0.167,0.167],"y":[0.167,0.167,0]},"t":205.205,"s":[70,70,100]},{"i":{"x":[0.833,0.833,0.833],"y":[0.833,0.833,1]},"o":{"x":[0.167,0.167,0.167],"y":[0.167,0.167,0]},"t":210.711,"s":[100,100,100]},{"i":{"x":[0.833,0.833,0.833],"y":[0.833,0.833,1]},"o":{"x":[0.167,0.167,0.167],"y":[0.167,0.167,0]},"t":215.215,"s":[70,70,100]},{"i":{"x":[0.833,0.833,0.833],"y":[0.833,0.833,1]},"o":{"x":[0.167,0.167,0.167],"y":[0.167,0.167,0]},"t":220.721,"s":[100,100,100]},{"i":{"x":[0.833,0.833,0.833],"y":[0.833,0.833,1]},"o":{"x":[0.167,0.167,0.167],"y":[0.167,0.167,0]},"t":225.225,"s":[70,70,100]},{"i":{"x":[0.833,0.833,0.833],"y":[0.833,0.833,1]},"o":{"x":[0.167,0.167,0.167],"y":[0.167,0.167,0]},"t":230.731,"s":[100,100,100]},{"i":{"x":[0.833,0.833,0.833],"y":[0.833,0.833,1]},"o":{"x":[0.167,0.167,0.167],"y":[0.167,0.167,0]},"t":235.235,"s":[70,70,100]},{"i":{"x":[0.833,0.833,0.833],"y":[0.833,0.833,1]},"o":{"x":[0.167,0.167,0.167],"y":[0.167,0.167,0]},"t":240.741,"s":[100,100,100]},{"i":{"x":[0.833,0.833,0.833],"y":[0.833,0.833,1]},"o":{"x":[0.167,0.167,0.167],"y":[0.167,0.167,0]},"t":245.245,"s":[70,70,100]},{"i":{"x":[0.833,0.833,0.833],"y":[0.833,0.833,1]},"o":{"x":[0.167,0.167,0.167],"y":[0.167,0.167,0]},"t":250.751,"s":[100,100,100]},{"i":{"x":[0.833,0.833,0.833],"y":[0.833,0.833,1]},"o":{"x":[0.167,0.167,0.167],"y":[0.167,0.167,0]},"t":255.255,"s":[70,70,100]},{"i":{"x":[0.833,0.833,0.833],"y":[0.833,0.833,1]},"o":{"x":[0.167,0.167,0.167],"y":[0.167,0.167,0]},"t":260.761,"s":[100,100,100]},{"i":{"x":[0.833,0.833,0.833],"y":[0.833,0.833,1]},"o":{"x":[0.167,0.167,0.167],"y":[0.167,0.167,0]},"t":265.265,"s":[70,70,100]},{"i":{"x":[0.833,0.833,0.833],"y":[0.833,0.833,1]},"o":{"x":[0.167,0.167,0.167],"y":[0.167,0.167,0]},"t":270.771,"s":[100,100,100]},{"i":{"x":[0.833,0.833,0.833],"y":[0.833,0.833,1]},"o":{"x":[0.167,0.167,0.167],"y":[0.167,0.167,0]},"t":275.275,"s":[70,70,100]},{"i":{"x":[0.833,0.833,0.833],"y":[0.833,0.833,1]},"o":{"x":[0.167,0.167,0.167],"y":[0.167,0.167,0]},"t":280.781,"s":[100,100,100]},{"i":{"x":[0.833,0.833,0.833],"y":[0.833,0.833,1]},"o":{"x":[0.167,0.167,0.167],"y":[0.167,0.167,0]},"t":285.285,"s":[70,70,100]},{"i":{"x":[0.833,0.833,0.833],"y":[0.833,0.833,1]},"o":{"x":[0.167,0.167,0.167],"y":[0.167,0.167,0]},"t":290.791,"s":[100,100,100]},{"i":{"x":[0.833,0.833,0.833],"y":[0.833,0.833,1]},"o":{"x":[0.167,0.167,0.167],"y":[0.167,0.167,0]},"t":295.295,"s":[70,70,100]},{"i":{"x":[0.833,0.833,0.833],"y":[0.833,0.833,1]},"o":{"x":[0.167,0.167,0.167],"y":[0.167,0.167,0]},"t":300.801,"s":[100,100,100]},{"i":{"x":[0.833,0.833,0.833],"y":[0.833,0.833,1]},"o":{"x":[0.167,0.167,0.167],"y":[0.167,0.167,0]},"t":305.305,"s":[70,70,100]},{"i":{"x":[0.833,0.833,0.833],"y":[0.833,0.833,1]},"o":{"x":[0.167,0.167,0.167],"y":[0.167,0.167,0]},"t":310.811,"s":[100,100,100]},{"i":{"x":[0.833,0.833,0.833],"y":[0.833,0.833,1]},"o":{"x":[0.167,0.167,0.167],"y":[0.167,0.167,0]},"t":315.315,"s":[70,70,100]},{"i":{"x":[0.833,0.833,0.833],"y":[0.833,0.833,1]},"o":{"x":[0.167,0.167,0.167],"y":[0.167,0.167,0]},"t":320.821,"s":[100,100,100]},{"i":{"x":[0.833,0.833,0.833],"y":[0.833,0.833,1]},"o":{"x":[0.167,0.167,0.167],"y":[0.167,0.167,0]},"t":325.325,"s":[70,70,100]},{"i":{"x":[0.833,0.833,0.833],"y":[0.833,0.833,1]},"o":{"x":[0.167,0.167,0.167],"y":[0.167,0.167,0]},"t":330.831,"s":[100,100,100]},{"i":{"x":[0.833,0.833,0.833],"y":[0.833,0.833,1]},"o":{"x":[0.167,0.167,0.167],"y":[0.167,0.167,0]},"t":335.335,"s":[70,70,100]},{"i":{"x":[0.833,0.833,0.833],"y":[0.833,0.833,1]},"o":{"x":[0.167,0.167,0.167],"y":[0.167,0.167,0]},"t":340.841,"s":[100,100,100]},{"i":{"x":[0.833,0.833,0.833],"y":[0.833,0.833,1]},"o":{"x":[0.167,0.167,0.167],"y":[0.167,0.167,0]},"t":345.345,"s":[70,70,100]},{"i":{"x":[0.833,0.833,0.833],"y":[0.833,0.833,1]},"o":{"x":[0.167,0.167,0.167],"y":[0.167,0.167,0]},"t":350.851,"s":[100,100,100]},{"i":{"x":[0.833,0.833,0.833],"y":[0.833,0.833,1]},"o":{"x":[0.167,0.167,0.167],"y":[0.167,0.167,0]},"t":355.355,"s":[70,70,100]},{"i":{"x":[0.833,0.833,0.833],"y":[0.833,0.833,1]},"o":{"x":[0.167,0.167,0.167],"y":[0.167,0.167,0]},"t":360.861,"s":[100,100,100]},{"i":{"x":[0.833,0.833,0.833],"y":[0.833,0.833,1]},"o":{"x":[0.167,0.167,0.167],"y":[0.167,0.167,0]},"t":365.365,"s":[70,70,100]},{"i":{"x":[0.833,0.833,0.833],"y":[0.833,0.833,1]},"o":{"x":[0.167,0.167,0.167],"y":[0.167,0.167,0]},"t":370.871,"s":[100,100,100]},{"i":{"x":[0.833,0.833,0.833],"y":[0.833,0.833,1]},"o":{"x":[0.167,0.167,0.167],"y":[0.167,0.167,0]},"t":375.375,"s":[70,70,100]},{"i":{"x":[0.833,0.833,0.833],"y":[0.833,0.833,1]},"o":{"x":[0.167,0.167,0.167],"y":[0.167,0.167,0]},"t":380.881,"s":[100,100,100]},{"i":{"x":[0.833,0.833,0.833],"y":[0.833,0.833,1]},"o":{"x":[0.167,0.167,0.167],"y":[0.167,0.167,0]},"t":385.385,"s":[70,70,100]},{"i":{"x":[0.833,0.833,0.833],"y":[0.833,0.833,1]},"o":{"x":[0.167,0.167,0.167],"y":[0.167,0.167,0]},"t":390.891,"s":[100,100,100]},{"i":{"x":[0.833,0.833,0.833],"y":[0.833,0.833,1]},"o":{"x":[0.167,0.167,0.167],"y":[0.167,0.167,0]},"t":395.395,"s":[70,70,100]},{"i":{"x":[0.833,0.833,0.833],"y":[0.833,0.833,1]},"o":{"x":[0.167,0.167,0.167],"y":[0.167,0.167,0]},"t":400.901,"s":[100,100,100]},{"i":{"x":[0.833,0.833,0.833],"y":[0.833,0.833,1]},"o":{"x":[0.167,0.167,0.167],"y":[0.167,0.167,0]},"t":405.405,"s":[70,70,100]},{"i":{"x":[0.833,0.833,0.833],"y":[0.833,0.833,1]},"o":{"x":[0.167,0.167,0.167],"y":[0.167,0.167,0]},"t":410.911,"s":[100,100,100]},{"i":{"x":[0.833,0.833,0.833],"y":[0.833,0.833,1]},"o":{"x":[0.167,0.167,0.167],"y":[0.167,0.167,0]},"t":415.415,"s":[70,70,100]},{"i":{"x":[0.833,0.833,0.833],"y":[0.833,0.833,1]},"o":{"x":[0.167,0.167,0.167],"y":[0.167,0.167,0]},"t":420.921,"s":[100,100,100]},{"i":{"x":[0.833,0.833,0.833],"y":[0.833,0.833,1]},"o":{"x":[0.167,0.167,0.167],"y":[0.167,0.167,0]},"t":425.425,"s":[70,70,100]},{"i":{"x":[0.833,0.833,0.833],"y":[0.833,0.833,1]},"o":{"x":[0.167,0.167,0.167],"y":[0.167,0.167,0]},"t":430.931,"s":[100,100,100]},{"i":{"x":[0.833,0.833,0.833],"y":[0.833,0.833,1]},"o":{"x":[0.167,0.167,0.167],"y":[0.167,0.167,0]},"t":435.435,"s":[70,70,100]},{"i":{"x":[0.833,0.833,0.833],"y":[0.833,0.833,1]},"o":{"x":[0.167,0.167,0.167],"y":[0.167,0.167,0]},"t":440.941,"s":[100,100,100]},{"i":{"x":[0.833,0.833,0.833],"y":[0.833,0.833,1]},"o":{"x":[0.167,0.167,0.167],"y":[0.167,0.167,0]},"t":445.445,"s":[70,70,100]},{"i":{"x":[0.833,0.833,0.833],"y":[0.833,0.833,1]},"o":{"x":[0.167,0.167,0.167],"y":[0.167,0.167,0]},"t":450.951,"s":[100,100,100]},{"i":{"x":[0.833,0.833,0.833],"y":[0.833,0.833,1]},"o":{"x":[0.167,0.167,0.167],"y":[0.167,0.167,0]},"t":455.455,"s":[70,70,100]},{"i":{"x":[0.833,0.833,0.833],"y":[0.833,0.833,1]},"o":{"x":[0.167,0.167,0.167],"y":[0.167,0.167,0]},"t":460.961,"s":[100,100,100]},{"i":{"x":[0.833,0.833,0.833],"y":[0.833,0.833,1]},"o":{"x":[0.167,0.167,0.167],"y":[0.167,0.167,0]},"t":465.465,"s":[70,70,100]},{"i":{"x":[0.833,0.833,0.833],"y":[0.833,0.833,1]},"o":{"x":[0.167,0.167,0.167],"y":[0.167,0.167,0]},"t":470.971,"s":[100,100,100]},{"i":{"x":[0.833,0.833,0.833],"y":[0.833,0.833,1]},"o":{"x":[0.167,0.167,0.167],"y":[0.167,0.167,0]},"t":475.475,"s":[70,70,100]},{"i":{"x":[0.833,0.833,0.833],"y":[0.833,0.833,1]},"o":{"x":[0.167,0.167,0.167],"y":[0.167,0.167,0]},"t":480.981,"s":[100,100,100]},{"i":{"x":[0.833,0.833,0.833],"y":[0.833,0.833,1]},"o":{"x":[0.167,0.167,0.167],"y":[0.167,0.167,0]},"t":485.485,"s":[70,70,100]},{"i":{"x":[0.833,0.833,0.833],"y":[0.833,0.833,1]},"o":{"x":[0.167,0.167,0.167],"y":[0.167,0.167,0]},"t":490.991,"s":[100,100,100]},{"i":{"x":[0.833,0.833,0.833],"y":[0.833,0.833,1]},"o":{"x":[0.167,0.167,0.167],"y":[0.167,0.167,0]},"t":495.495,"s":[70,70,100]},{"i":{"x":[0.833,0.833,0.833],"y":[0.833,0.833,1]},"o":{"x":[0.167,0.167,0.167],"y":[0.167,0.167,0]},"t":501.001,"s":[100,100,100]},{"i":{"x":[0.833,0.833,0.833],"y":[0.833,0.833,1]},"o":{"x":[0.167,0.167,0.167],"y":[0.167,0.167,0]},"t":505.506,"s":[70,70,100]},{"i":{"x":[0.833,0.833,0.833],"y":[0.833,0.833,1]},"o":{"x":[0.167,0.167,0.167],"y":[0.167,0.167,0]},"t":511.011,"s":[100,100,100]},{"i":{"x":[0.833,0.833,0.833],"y":[0.833,0.833,1]},"o":{"x":[0.167,0.167,0.167],"y":[0.167,0.167,0]},"t":515.516,"s":[70,70,100]},{"i":{"x":[0.833,0.833,0.833],"y":[0.833,0.833,1]},"o":{"x":[0.167,0.167,0.167],"y":[0.167,0.167,0]},"t":521.021,"s":[100,100,100]},{"i":{"x":[0.833,0.833,0.833],"y":[0.833,0.833,1]},"o":{"x":[0.167,0.167,0.167],"y":[0.167,0.167,0]},"t":525.526,"s":[70,70,100]},{"i":{"x":[0.833,0.833,0.833],"y":[0.833,0.833,1]},"o":{"x":[0.167,0.167,0.167],"y":[0.167,0.167,0]},"t":531.031,"s":[100,100,100]},{"i":{"x":[0.833,0.833,0.833],"y":[0.833,0.833,1]},"o":{"x":[0.167,0.167,0.167],"y":[0.167,0.167,0]},"t":535.536,"s":[70,70,100]},{"i":{"x":[0.833,0.833,0.833],"y":[0.833,0.833,1]},"o":{"x":[0.167,0.167,0.167],"y":[0.167,0.167,0]},"t":541.041,"s":[100,100,100]},{"i":{"x":[0.833,0.833,0.833],"y":[0.833,0.833,1]},"o":{"x":[0.167,0.167,0.167],"y":[0.167,0.167,0]},"t":545.546,"s":[70,70,100]},{"i":{"x":[0.833,0.833,0.833],"y":[0.833,0.833,1]},"o":{"x":[0.167,0.167,0.167],"y":[0.167,0.167,0]},"t":551.051,"s":[100,100,100]},{"i":{"x":[0.833,0.833,0.833],"y":[0.833,0.833,1]},"o":{"x":[0.167,0.167,0.167],"y":[0.167,0.167,0]},"t":555.556,"s":[70,70,100]},{"i":{"x":[0.833,0.833,0.833],"y":[0.833,0.833,1]},"o":{"x":[0.167,0.167,0.167],"y":[0.167,0.167,0]},"t":561.061,"s":[100,100,100]},{"i":{"x":[0.833,0.833,0.833],"y":[0.833,0.833,1]},"o":{"x":[0.167,0.167,0.167],"y":[0.167,0.167,0]},"t":565.566,"s":[70,70,100]},{"i":{"x":[0.833,0.833,0.833],"y":[0.833,0.833,1]},"o":{"x":[0.167,0.167,0.167],"y":[0.167,0.167,0]},"t":571.071,"s":[100,100,100]},{"i":{"x":[0.833,0.833,0.833],"y":[0.833,0.833,1]},"o":{"x":[0.167,0.167,0.167],"y":[0.167,0.167,0]},"t":575.576,"s":[70,70,100]},{"i":{"x":[0.833,0.833,0.833],"y":[0.833,0.833,1]},"o":{"x":[0.167,0.167,0.167],"y":[0.167,0.167,0]},"t":581.081,"s":[100,100,100]},{"i":{"x":[0.833,0.833,0.833],"y":[0.833,0.833,1]},"o":{"x":[0.167,0.167,0.167],"y":[0.167,0.167,0]},"t":585.586,"s":[70,70,100]},{"i":{"x":[0.833,0.833,0.833],"y":[0.833,0.833,1]},"o":{"x":[0.167,0.167,0.167],"y":[0.167,0.167,0]},"t":591.091,"s":[100,100,100]},{"i":{"x":[0.833,0.833,0.833],"y":[0.833,0.833,1]},"o":{"x":[0.167,0.167,0.167],"y":[0.167,0.167,0]},"t":595.596,"s":[70,70,100]},{"i":{"x":[0.833,0.833,0.833],"y":[0.833,0.833,1]},"o":{"x":[0.167,0.167,0.167],"y":[0.167,0.167,0]},"t":601.101,"s":[100,100,100]},{"i":{"x":[0.833,0.833,0.833],"y":[0.833,0.833,1]},"o":{"x":[0.167,0.167,0.167],"y":[0.167,0.167,0]},"t":605.606,"s":[70,70,100]},{"i":{"x":[0.833,0.833,0.833],"y":[0.833,0.833,1]},"o":{"x":[0.167,0.167,0.167],"y":[0.167,0.167,0]},"t":611.111,"s":[100,100,100]},{"i":{"x":[0.833,0.833,0.833],"y":[0.833,0.833,1]},"o":{"x":[0.167,0.167,0.167],"y":[0.167,0.167,0]},"t":615.616,"s":[70,70,100]},{"i":{"x":[0.833,0.833,0.833],"y":[0.833,0.833,1]},"o":{"x":[0.167,0.167,0.167],"y":[0.167,0.167,0]},"t":621.121,"s":[100,100,100]},{"i":{"x":[0.833,0.833,0.833],"y":[0.833,0.833,1]},"o":{"x":[0.167,0.167,0.167],"y":[0.167,0.167,0]},"t":625.626,"s":[70,70,100]},{"i":{"x":[0.833,0.833,0.833],"y":[0.833,0.833,1]},"o":{"x":[0.167,0.167,0.167],"y":[0.167,0.167,0]},"t":631.131,"s":[100,100,100]},{"i":{"x":[0.833,0.833,0.833],"y":[0.833,0.833,1]},"o":{"x":[0.167,0.167,0.167],"y":[0.167,0.167,0]},"t":635.636,"s":[70,70,100]},{"i":{"x":[0.833,0.833,0.833],"y":[0.833,0.833,1]},"o":{"x":[0.167,0.167,0.167],"y":[0.167,0.167,0]},"t":641.141,"s":[100,100,100]},{"i":{"x":[0.833,0.833,0.833],"y":[0.833,0.833,1]},"o":{"x":[0.167,0.167,0.167],"y":[0.167,0.167,0]},"t":645.646,"s":[70,70,100]},{"i":{"x":[0.833,0.833,0.833],"y":[0.833,0.833,1]},"o":{"x":[0.167,0.167,0.167],"y":[0.167,0.167,0]},"t":651.151,"s":[100,100,100]},{"i":{"x":[0.833,0.833,0.833],"y":[0.833,0.833,1]},"o":{"x":[0.167,0.167,0.167],"y":[0.167,0.167,0]},"t":655.656,"s":[70,70,100]},{"i":{"x":[0.833,0.833,0.833],"y":[0.833,0.833,1]},"o":{"x":[0.167,0.167,0.167],"y":[0.167,0.167,0]},"t":661.161,"s":[100,100,100]},{"i":{"x":[0.833,0.833,0.833],"y":[0.833,0.833,1]},"o":{"x":[0.167,0.167,0.167],"y":[0.167,0.167,0]},"t":665.666,"s":[70,70,100]},{"i":{"x":[0.833,0.833,0.833],"y":[0.833,0.833,1]},"o":{"x":[0.167,0.167,0.167],"y":[0.167,0.167,0]},"t":671.171,"s":[100,100,100]},{"i":{"x":[0.833,0.833,0.833],"y":[0.833,0.833,1]},"o":{"x":[0.167,0.167,0.167],"y":[0.167,0.167,0]},"t":675.676,"s":[70,70,100]},{"i":{"x":[0.833,0.833,0.833],"y":[0.833,0.833,1]},"o":{"x":[0.167,0.167,0.167],"y":[0.167,0.167,0]},"t":681.181,"s":[100,100,100]},{"i":{"x":[0.833,0.833,0.833],"y":[0.833,0.833,1]},"o":{"x":[0.167,0.167,0.167],"y":[0.167,0.167,0]},"t":685.686,"s":[70,70,100]},{"i":{"x":[0.833,0.833,0.833],"y":[0.833,0.833,1]},"o":{"x":[0.167,0.167,0.167],"y":[0.167,0.167,0]},"t":691.191,"s":[100,100,100]},{"i":{"x":[0.833,0.833,0.833],"y":[0.833,0.833,1]},"o":{"x":[0.167,0.167,0.167],"y":[0.167,0.167,0]},"t":695.696,"s":[70,70,100]},{"i":{"x":[0.833,0.833,0.833],"y":[0.833,0.833,1]},"o":{"x":[0.167,0.167,0.167],"y":[0.167,0.167,0]},"t":701.201,"s":[100,100,100]},{"i":{"x":[0.833,0.833,0.833],"y":[0.833,0.833,1]},"o":{"x":[0.167,0.167,0.167],"y":[0.167,0.167,0]},"t":705.706,"s":[70,70,100]},{"t":711.211211211211,"s":[100,100,100]}],"ix":6,"l":2}},"ao":0,"shapes":[{"ty":"gr","it":[{"ind":0,"ty":"sh","ix":1,"ks":{"a":0,"k":{"i":[[-0.01,-0.465],[0.693,-0.981],[1.559,2.199],[-0.011,0.857],[0,0],[0.289,-0.371],[0,-1.549],[0,0],[0,3.717],[0.887,1.136]],"o":[[0,0.867],[-1.558,2.199],[-0.692,-0.981],[0,0],[0,-0.475],[-0.888,1.137],[0,3.718],[0,0],[0,-1.57],[-0.3,-0.361]],"v":[[4.415,-6.976],[3.195,-4.105],[-3.206,-4.105],[-4.424,-6.955],[-4.424,-6.976],[-5.303,-7.276],[-6.728,-3.145],[-0.005,7.647],[6.728,-3.155],[5.303,-7.286]],"c":true},"ix":2},"nm":"Tracé 1","mn":"ADBE Vector Shape - Group","hd":false},{"ty":"fl","c":{"a":0,"k":[1,1,1,1],"ix":4},"o":{"a":0,"k":100,"ix":5},"r":1,"bm":0,"nm":"Fill 1","mn":"ADBE Vector Graphic - Fill","hd":false},{"ty":"tr","p":{"a":0,"k":[6.978,7.897],"ix":2},"a":{"a":0,"k":[0,0],"ix":1},"s":{"a":0,"k":[100,100],"ix":3},"r":{"a":0,"k":0,"ix":6},"o":{"a":0,"k":100,"ix":7},"sk":{"a":0,"k":0,"ix":4},"sa":{"a":0,"k":0,"ix":5},"nm":"Transformer "}],"nm":"Group 1","np":2,"cix":2,"bm":0,"ix":1,"mn":"ADBE Vector Group","hd":false}],"ip":0,"op":720.720720720721,"st":0,"ct":1,"bm":0}]}],"layers":[{"ddd":0,"ind":2,"ty":3,"nm":"Null 1","sr":1,"ks":{"o":{"a":0,"k":0,"ix":11},"r":{"a":0,"k":0,"ix":10},"p":{"a":1,"k":[{"i":{"x":0.833,"y":0.833},"o":{"x":0.167,"y":0.167},"t":399.492,"s":[185,2501.788,0],"to":[0,0.034,0],"ti":[0.002,-0.948,0]},{"t":432,"s":[185.008,3320.966,0]}],"ix":2,"l":2},"a":{"a":0,"k":[0,0,0],"ix":1,"l":2},"s":{"a":0,"k":[100,100,100],"ix":6,"l":2}},"ao":0,"ip":0,"op":720.720720720721,"st":0,"bm":0},{"ddd":0,"ind":3,"ty":0,"nm":"stars","parent":2,"refId":"comp_0","sr":1,"ks":{"o":{"a":0,"k":70,"ix":11},"r":{"a":0,"k":-180,"ix":10},"p":{"a":0,"k":[0,-3469.965,0],"ix":2,"l":2},"a":{"a":0,"k":[185,209,0],"ix":1,"l":2},"s":{"a":0,"k":[100,100,100],"ix":6,"l":2}},"ao":0,"w":370,"h":418,"ip":0,"op":720.720720720721,"st":0,"bm":0},{"ddd":0,"ind":4,"ty":0,"nm":"stars","parent":2,"refId":"comp_0","sr":1,"ks":{"o":{"a":0,"k":70,"ix":11},"r":{"a":0,"k":180,"ix":10},"p":{"a":0,"k":[0,-3049.965,0],"ix":2,"l":2},"a":{"a":0,"k":[185,209,0],"ix":1,"l":2},"s":{"a":0,"k":[100,100,100],"ix":6,"l":2}},"ao":0,"w":370,"h":418,"ip":0,"op":720.720720720721,"st":0,"bm":0},{"ddd":0,"ind":5,"ty":0,"nm":"stars","parent":2,"refId":"comp_0","sr":1,"ks":{"o":{"a":0,"k":70,"ix":11},"r":{"a":0,"k":-180,"ix":10},"p":{"a":0,"k":[0,-2637.965,0],"ix":2,"l":2},"a":{"a":0,"k":[185,209,0],"ix":1,"l":2},"s":{"a":0,"k":[100,100,100],"ix":6,"l":2}},"ao":0,"w":370,"h":418,"ip":0,"op":720.720720720721,"st":0,"bm":0},{"ddd":0,"ind":6,"ty":0,"nm":"stars","parent":2,"refId":"comp_0","sr":1,"ks":{"o":{"a":0,"k":70,"ix":11},"r":{"a":0,"k":180,"ix":10},"p":{"a":0,"k":[0,-2217.965,0],"ix":2,"l":2},"a":{"a":0,"k":[185,209,0],"ix":1,"l":2},"s":{"a":0,"k":[100,100,100],"ix":6,"l":2}},"ao":0,"w":370,"h":418,"ip":0,"op":720.720720720721,"st":0,"bm":0},{"ddd":0,"ind":7,"ty":0,"nm":"stars","parent":2,"refId":"comp_0","sr":1,"ks":{"o":{"a":0,"k":70,"ix":11},"r":{"a":0,"k":0,"ix":10},"p":{"a":0,"k":[0,-1797.965,0],"ix":2,"l":2},"a":{"a":0,"k":[185,209,0],"ix":1,"l":2},"s":{"a":0,"k":[100,100,100],"ix":6,"l":2}},"ao":0,"w":370,"h":418,"ip":0,"op":720.720720720721,"st":0,"bm":0},{"ddd":0,"ind":8,"ty":0,"nm":"ion-ios-rocket","refId":"comp_1","sr":1,"ks":{"o":{"a":0,"k":100,"ix":11},"r":{"a":0,"k":0,"ix":10},"p":{"a":1,"k":[{"i":{"x":0.667,"y":1},"o":{"x":0.333,"y":0},"t":155.154,"s":[185,216.5,0],"to":[0,-4.833,0],"ti":[0,-3.35,0]},{"i":{"x":0.667,"y":1},"o":{"x":0.333,"y":0},"t":204.205,"s":[185,187.5,0],"to":[0,3.35,0],"ti":[0,0,0]},{"i":{"x":0.667,"y":1},"o":{"x":0.333,"y":0},"t":250.25,"s":[185,236.6,0],"to":[0,0,0],"ti":[0,0,0]},{"i":{"x":0.667,"y":1},"o":{"x":0.333,"y":0},"t":299.299,"s":[185,187.5,0],"to":[0,0,0],"ti":[0,0,0]},{"i":{"x":0.667,"y":1},"o":{"x":0.333,"y":0},"t":345.346,"s":[185,236.6,0],"to":[0,0,0],"ti":[0,0,0]},{"i":{"x":0.667,"y":1},"o":{"x":0.333,"y":0},"t":399,"s":[185,187.5,0],"to":[0,0,0],"ti":[0,0,0]},{"i":{"x":0.667,"y":1},"o":{"x":0.333,"y":0},"t":414.957,"s":[185,236.6,0],"to":[0,0,0],"ti":[0,0,0]},{"i":{"x":0.667,"y":1},"o":{"x":0.333,"y":0},"t":431.508,"s":[185,187.5,0],"to":[0,0,0],"ti":[0,0,0]},{"i":{"x":0.667,"y":1},"o":{"x":0.333,"y":0},"t":532.533,"s":[185,236.6,0],"to":[0,0,0],"ti":[0,0,0]},{"i":{"x":0.341,"y":1},"o":{"x":0.333,"y":0},"t":578.578,"s":[185,187.5,0],"to":[0,0,0],"ti":[0,0,0]},{"i":{"x":0.667,"y":1},"o":{"x":1,"y":0},"t":624.625,"s":[185,236.6,0],"to":[0,0,0],"ti":[0,77.833,0]},{"t":644.64453125,"s":[185,-230.4,0]}],"ix":2,"l":2},"a":{"a":0,"k":[53,53.5,0],"ix":1,"l":2},"s":{"a":1,"k":[{"i":{"x":[0.667,0.667,0.667],"y":[1,1,1]},"o":{"x":[0.333,0.333,0.333],"y":[0,0,0]},"t":140.141,"s":[0,0,100]},{"i":{"x":[0.667,0.667,0.667],"y":[1,1,1]},"o":{"x":[0.333,0.333,0.333],"y":[0,0,0]},"t":149.148,"s":[280,280,100]},{"t":155.154296875,"s":[250,250,100]}],"ix":6,"l":2}},"ao":0,"w":106,"h":107,"ip":0,"op":720.720720720721,"st":0,"bm":0}],"markers":[],"props":{}}